{
  "@context": "https://linked.art/ns/v1/linked-art.json",
  "id": "https://linkedart.example.com/exhibition/806",
  "type": "Activity",
  "_label": "Americans 1963",
  "classified_as": [
    {
      "id": "http://vocab.getty.edu/aat/300054766",
      "type": "Type",
      "_label": "Exhibiting"
    }
  ],
  "identified_by": [
    {
      "type": "Name",
      "_label": "Americans 1963",
      "classified_as": [
        {
          "id": "http://vocab.getty.edu/aat/300404670",
          "type": "Type",
          "_label": "Owner-Assigned Title"
        }
      ]
    }
  ],
  "timespan": {
    "type": "TimeSpan",
    "begin_of_the_begin": "1963-22-5",
    "end_of_the_end": "1963-18-8"
  },
  "took_place_at": [
    {
      "id": "https://linkedart.example.com/Place/3958",
      "type": "Place",
      "_label": "11 West 53rd St.",
      "classified_as": [
        {
          "id": "http://vocab.getty.edu/aat/300005768",
          "type": "Type",
          "_label": "Museum (place)"
        }
      ]
    }
  ],
  "part": [
    {
      "id": "https://linkedart.example.com/AttributeAssignment/3958",
      "type": "AttributeAssignment",
      "involved": [
        {
          "id": "https://linkedart.example.com/Set/3958",
          "type": "Set",
          "_label": "Persons",
          "about": [
            {
              "id": "https://linkedart.example.com/Person/40569",
              "type": "Person",
              "_label": "David Simpson"
            },
            {
              "id": "https://linkedart.example.com/Person/40570",
              "type": "Person",
              "_label": "Gabriel Kohn"
            },
            {
              "id": "https://linkedart.example.com/Person/40571",
              "type": "Person",
              "_label": "James Rosenquist"
            },
            {
              "id": "https://linkedart.example.com/Person/40572",
              "type": "Person",
              "_label": "Marisol (Marisol Escobar)"
            },
            {
              "id": "https://linkedart.example.com/Person/40573",
              "type": "Person",
              "_label": "Jason Seley"
            },
            {
              "id": "https://linkedart.example.com/Person/40574",
              "type": "Person",
              "_label": "Michael Lekakis"
            },
            {
              "id": "https://linkedart.example.com/Person/40575",
              "type": "Person",
              "_label": "Ad Reinhardt"
            },
            {
              "id": "https://linkedart.example.com/Person/40576",
              "type": "Person",
              "_label": "Richard Lindner"
            },
            {
              "id": "https://linkedart.example.com/Person/40577",
              "type": "Person",
              "_label": "Claes Oldenburg"
            },
            {
              "id": "https://linkedart.example.com/Person/40578",
              "type": "Person",
              "_label": "Dorothy C. Miller"
            },
            {
              "id": "https://linkedart.example.com/Person/40579",
              "type": "Person",
              "_label": "Robert Indiana"
            },
            {
              "id": "https://linkedart.example.com/Person/40580",
              "type": "Person",
              "_label": "Richard Anuszkiewicz"
            },
            {
              "id": "https://linkedart.example.com/Person/40581",
              "type": "Person",
              "_label": "Lee Bontecou"
            },
            {
              "id": "https://linkedart.example.com/Person/40582",
              "type": "Person",
              "_label": "Chryssa"
            },
            {
              "id": "https://linkedart.example.com/Person/40583",
              "type": "Person",
              "_label": "Edward Higgins"
            },
            {
              "id": "https://linkedart.example.com/Person/40584",
              "type": "Person",
              "_label": "Sally Hazelet Drummond"
            }
          ]
        }
      ]
    }
  ]
}