{
  "@context": "https://linked.art/ns/v1/linked-art.json",
  "id": "http://linkedart.example.com/person/1951",
  "type": "Person",
  "_label": "Barbara E. Fumagalli",
  "identified_by": [
    {
      "id": "https://linkedart.example.com/Name/4806",
      "type": "Name",
      "_label": "Barbara E. Fumagalli"
    },
    {
      "id": "https://linkedart.example.com/Name/4807",
      "type": "Name",
      "_label": "Fumagalli Barbara E."
    },
    {
      "id": "http://vocab.getty.edu/page/ulan/",
      "type": "Identifier",
      "_label": "ULAN Identifier"
    },
    {
      "id": "https://viaf.org/viaf/",
      "type": "Identifier",
      "_label": "VIAF Identifier"
    },
    {
      "id": "https://www.wikidata.org/wiki/",
      "type": "Identifier",
      "_label": "Wikidata Identifier"
    }
  ],
  "referred_to_by": [
    {
      "id": "https://linkedart.example.com/LinguisticObject/2050",
      "type": "LinguisticObject",
      "classified_as": [
        {
          "id": "http://vocab.getty.edu/aat/300435422",
          "type": "Type",
          "_label": "Biography Statement"
        }
      ],
      "content": "American"
    }
  ],
  "born": {
    "id": "https://linkedart.example.com/Birth/2403",
    "type": "Birth",
    "_label": "Birth",
    "timespan": {
      "id": "https://linkedart.example.com/TimeSpan/4806",
      "type": "TimeSpan",
      "_label": "Barbara E. Fumagalli Birth timespan"
    }
  },
  "died": {
    "id": "https://linkedart.example.com/Death/2403",
    "type": "Death",
    "_label": "Death",
    "timespan": {
      "id": "https://linkedart.example.com/TimeSpan/4807",
      "type": "TimeSpan",
      "_label": "Barbara E. Fumagalli Death timespan"
    }
  },
  "assigned_by": [
    {
      "id": "https://linkedart.example.com/AttributeAssignment/2403",
      "type": "AttributeAssignment",
      "involved": [
        {
          "id": "https://linkedart.example.com/Set/2403",
          "type": "Set",
          "_label": "Exhibitions",
          "about": [
            {
              "id": "http://linkedart.example.com/exhibition/2670",
              "type": "Event",
              "_label": "Summer Exhibition: New Acquisitions; Recent American Prints, 1947–1953; Katherine S. Dreier Bequest; Kuniyoshi and Spencer; Expressionism in Germany; Varieties of Realism",
              "timespan": {
                "type": "TimeSpan",
                "_label": "1953-23-6 - 1953-4-10",
                "begin_of_the_begin": "1953-23-6",
                "end_of_the_end": "1953-4-10"
              },
              "took_place_at": [
                {
                  "id": "https://linkedart.example.com/Place/11269",
                  "type": "Place",
                  "_label": "3rd Floor, 11 West 53rd St.",
                  "classified_as": [
                    {
                      "id": "http://vocab.getty.edu/aat/300005768",
                      "type": "Type",
                      "_label": "Museum (place)"
                    }
                  ]
                }
              ]
            },
            {
              "id": "http://linkedart.example.com/exhibition/615",
              "type": "Event",
              "_label": "Young American Printmakers",
              "timespan": {
                "type": "TimeSpan",
                "_label": "1953-25-11 - 1954-31-1",
                "begin_of_the_begin": "1953-25-11",
                "end_of_the_end": "1954-31-1"
              },
              "took_place_at": [
                {
                  "id": "https://linkedart.example.com/Place/11270",
                  "type": "Place",
                  "classified_as": [
                    {
                      "id": "http://vocab.getty.edu/aat/300005768",
                      "type": "Type",
                      "_label": "Museum (place)"
                    }
                  ]
                }
              ]
            },
            {
              "id": "http://linkedart.example.com/exhibition/634",
              "type": "Event",
              "_label": "American Prints of the 20th Century",
              "timespan": {
                "type": "TimeSpan",
                "_label": "1954-8-9 - 1954-28-11",
                "begin_of_the_begin": "1954-8-9",
                "end_of_the_end": "1954-28-11"
              },
              "took_place_at": [
                {
                  "id": "https://linkedart.example.com/Place/11271",
                  "type": "Place",
                  "classified_as": [
                    {
                      "id": "http://vocab.getty.edu/aat/300005768",
                      "type": "Type",
                      "_label": "Museum (place)"
                    }
                  ]
                }
              ]
            }
          ]
        }
      ]
    }
  ]
}