{
  "@context": "https://linked.art/ns/v1/linked-art.json",
  "id": "http://linkedart.example.com/person/2567",
  "type": "Person",
  "_label": "Rick McKee Hock",
  "identified_by": [
    {
      "id": "https://linkedart.example.com/Name/10016",
      "type": "Name",
      "_label": "Rick McKee Hock"
    },
    {
      "id": "https://linkedart.example.com/Name/10017",
      "type": "Name",
      "_label": "Hock Rick McKee"
    },
    {
      "id": "http://vocab.getty.edu/page/ulan/500333554",
      "type": "Identifier",
      "_label": "ULAN Identifier"
    },
    {
      "id": "https://viaf.org/viaf/Q55218945",
      "type": "Identifier",
      "_label": "VIAF Identifier"
    },
    {
      "id": "https://www.wikidata.org/wiki/Q55218945",
      "type": "Identifier",
      "_label": "Wikidata Identifier"
    }
  ],
  "referred_to_by": [
    {
      "id": "https://linkedart.example.com/LinguisticObject/4218",
      "type": "LinguisticObject",
      "classified_as": [
        {
          "id": "http://vocab.getty.edu/aat/300435422",
          "type": "Type",
          "_label": "Biography Statement"
        }
      ],
      "content": "American, born 1949"
    }
  ],
  "born": {
    "id": "https://linkedart.example.com/Birth/5008",
    "type": "Birth",
    "_label": "Birth",
    "timespan": {
      "id": "https://linkedart.example.com/TimeSpan/10016",
      "type": "TimeSpan",
      "_label": "Rick McKee Hock Birth timespan",
      "begin_of_the_begin": "1949",
      "end_of_the_end": "1949"
    }
  },
  "died": {
    "id": "https://linkedart.example.com/Death/5008",
    "type": "Death",
    "_label": "Death",
    "timespan": {
      "id": "https://linkedart.example.com/TimeSpan/10017",
      "type": "TimeSpan",
      "_label": "Rick McKee Hock Death timespan"
    }
  },
  "assigned_by": [
    {
      "id": "https://linkedart.example.com/AttributeAssignment/5008",
      "type": "AttributeAssignment",
      "involved": [
        {
          "id": "https://linkedart.example.com/Set/5008",
          "type": "Set",
          "_label": "Exhibitions",
          "about": [
            {
              "id": "http://linkedart.example.com/exhibition/1913",
              "type": "Event",
              "_label": "Multiple Images: Photographs Since 1965 from the Collection",
              "timespan": {
                "type": "TimeSpan",
                "_label": "1993-15-7 - 1993-5-10",
                "begin_of_the_begin": "1993-15-7",
                "end_of_the_end": "1993-5-10"
              },
              "took_place_at": [
                {
                  "id": "https://linkedart.example.com/Place/20215",
                  "type": "Place",
                  "_label": "11 West 53rd St.",
                  "classified_as": [
                    {
                      "id": "http://vocab.getty.edu/aat/300005768",
                      "type": "Type",
                      "_label": "Museum (place)"
                    }
                  ]
                }
              ]
            }
          ]
        }
      ]
    }
  ]
}