{
  "@context": "https://linked.art/ns/v1/linked-art.json",
  "id": "http://linkedart.example.com/person/5927",
  "type": "Person",
  "_label": "Edward Wadsworth",
  "identified_by": [
    {
      "id": "https://linkedart.example.com/Name/35760",
      "type": "Name",
      "_label": "Edward Wadsworth"
    },
    {
      "id": "https://linkedart.example.com/Name/35761",
      "type": "Name",
      "_label": "Wadsworth Edward"
    },
    {
      "id": "http://vocab.getty.edu/page/ulan/500028119",
      "type": "Identifier",
      "_label": "ULAN Identifier"
    },
    {
      "id": "https://viaf.org/viaf/Q1294022",
      "type": "Identifier",
      "_label": "VIAF Identifier"
    },
    {
      "id": "https://www.wikidata.org/wiki/Q1294022",
      "type": "Identifier",
      "_label": "Wikidata Identifier"
    }
  ],
  "referred_to_by": [
    {
      "id": "https://linkedart.example.com/LinguisticObject/7798",
      "type": "LinguisticObject",
      "classified_as": [
        {
          "id": "http://vocab.getty.edu/aat/300435422",
          "type": "Type",
          "_label": "Biography Statement"
        }
      ],
      "content": "British, 1889–1949"
    }
  ],
  "born": {
    "id": "https://linkedart.example.com/Birth/17880",
    "type": "Birth",
    "_label": "Birth",
    "timespan": {
      "id": "https://linkedart.example.com/TimeSpan/35760",
      "type": "TimeSpan",
      "_label": "Edward Wadsworth Birth timespan",
      "begin_of_the_begin": "1889",
      "end_of_the_end": "1889"
    }
  },
  "died": {
    "id": "https://linkedart.example.com/Death/17880",
    "type": "Death",
    "_label": "Death",
    "timespan": {
      "id": "https://linkedart.example.com/TimeSpan/35761",
      "type": "TimeSpan",
      "_label": "Edward Wadsworth Death timespan",
      "begin_of_the_begin": "1949",
      "end_of_the_end": "1949"
    }
  },
  "assigned_by": [
    {
      "id": "https://linkedart.example.com/AttributeAssignment/17880",
      "type": "AttributeAssignment",
      "involved": [
        {
          "id": "https://linkedart.example.com/Set/17880",
          "type": "Set",
          "_label": "Exhibitions",
          "about": [
            {
              "id": "http://linkedart.example.com/exhibition/177",
              "type": "Event",
              "_label": "Britain at War",
              "timespan": {
                "type": "TimeSpan",
                "_label": "1941-23-5 - 1941-2-9",
                "begin_of_the_begin": "1941-23-5",
                "end_of_the_end": "1941-2-9"
              },
              "took_place_at": [
                {
                  "id": "https://linkedart.example.com/Place/65180",
                  "type": "Place",
                  "_label": "11 West 53rd St.",
                  "classified_as": [
                    {
                      "id": "http://vocab.getty.edu/aat/300005768",
                      "type": "Type",
                      "_label": "Museum (place)"
                    }
                  ]
                }
              ]
            },
            {
              "id": "http://linkedart.example.com/exhibition/1533",
              "type": "Event",
              "_label": "Prints from Blocks: Gauguin to Now",
              "timespan": {
                "type": "TimeSpan",
                "_label": "1983-3-3 - 1983-15-5",
                "begin_of_the_begin": "1983-3-3",
                "end_of_the_end": "1983-15-5"
              },
              "took_place_at": [
                {
                  "id": "https://linkedart.example.com/Place/65181",
                  "type": "Place",
                  "_label": "West Wing Galleries, 11 West 53rd St.",
                  "classified_as": [
                    {
                      "id": "http://vocab.getty.edu/aat/300005768",
                      "type": "Type",
                      "_label": "Museum (place)"
                    }
                  ]
                }
              ]
            },
            {
              "id": "http://linkedart.example.com/exhibition/1738",
              "type": "Event",
              "_label": "Master Prints from the Collection",
              "timespan": {
                "type": "TimeSpan",
                "_label": "1989-6-4 - 1989-8-8",
                "begin_of_the_begin": "1989-6-4",
                "end_of_the_end": "1989-8-8"
              },
              "took_place_at": [
                {
                  "id": "https://linkedart.example.com/Place/65182",
                  "type": "Place",
                  "classified_as": [
                    {
                      "id": "http://vocab.getty.edu/aat/300005768",
                      "type": "Type",
                      "_label": "Museum (place)"
                    }
                  ]
                }
              ]
            },
            {
              "id": "http://linkedart.example.com/exhibition/1753",
              "type": "Event",
              "_label": "The Cubist Imprint",
              "timespan": {
                "type": "TimeSpan",
                "_label": "1989-18-8 - 1989-7-11",
                "begin_of_the_begin": "1989-18-8",
                "end_of_the_end": "1989-7-11"
              },
              "took_place_at": [
                {
                  "id": "https://linkedart.example.com/Place/65183",
                  "type": "Place",
                  "classified_as": [
                    {
                      "id": "http://vocab.getty.edu/aat/300005768",
                      "type": "Type",
                      "_label": "Museum (place)"
                    }
                  ]
                }
              ]
            },
            {
              "id": "http://linkedart.example.com/exhibition/1985",
              "type": "Event",
              "_label": "Adding It Up: Print Acquisitions 1970–1995",
              "timespan": {
                "type": "TimeSpan",
                "_label": "1995-27-5 - 1995-5-9",
                "begin_of_the_begin": "1995-27-5",
                "end_of_the_end": "1995-5-9"
              },
              "took_place_at": [
                {
                  "id": "https://linkedart.example.com/Place/65184",
                  "type": "Place",
                  "classified_as": [
                    {
                      "id": "http://vocab.getty.edu/aat/300005768",
                      "type": "Type",
                      "_label": "Museum (place)"
                    }
                  ]
                }
              ]
            }
          ]
        }
      ]
    }
  ]
}