{
  "@context": "https://linked.art/ns/v1/linked-art.json",
  "id": "http://linkedart.example.com/person/70755",
  "type": "Person",
  "_label": "nibia pastrana santiago",
  "identified_by": [
    {
      "id": "https://linkedart.example.com/Name/48952",
      "type": "Name",
      "_label": "nibia pastrana santiago"
    },
    {
      "id": "https://linkedart.example.com/Name/48953",
      "type": "Name",
      "_label": "santiago nibia pastrana"
    },
    {
      "id": "http://vocab.getty.edu/page/ulan/",
      "type": "Identifier",
      "_label": "ULAN Identifier"
    },
    {
      "id": "https://viaf.org/viaf/",
      "type": "Identifier",
      "_label": "VIAF Identifier"
    },
    {
      "id": "https://www.wikidata.org/wiki/",
      "type": "Identifier",
      "_label": "Wikidata Identifier"
    }
  ],
  "born": {
    "id": "https://linkedart.example.com/Birth/24476",
    "type": "Birth",
    "_label": "Birth",
    "timespan": {
      "id": "https://linkedart.example.com/TimeSpan/48952",
      "type": "TimeSpan",
      "_label": "nibia pastrana santiago Birth timespan"
    }
  },
  "died": {
    "id": "https://linkedart.example.com/Death/24476",
    "type": "Death",
    "_label": "Death",
    "timespan": {
      "id": "https://linkedart.example.com/TimeSpan/48953",
      "type": "TimeSpan",
      "_label": "nibia pastrana santiago Death timespan"
    }
  },
  "assigned_by": [
    {
      "id": "https://linkedart.example.com/AttributeAssignment/24476",
      "type": "AttributeAssignment",
      "involved": [
        {
          "id": "https://linkedart.example.com/Set/24476",
          "type": "Set",
          "_label": "Exhibitions",
          "about": [
            {
              "id": "http://linkedart.example.com/exhibition/28418",
              "type": "Event",
              "_label": "Whitney Biennial 2019",
              "timespan": {
                "type": "TimeSpan",
                "_label": "2019-17-5 - 2019-22-9",
                "begin_of_the_begin": "2019-17-5",
                "end_of_the_end": "2019-22-9"
              },
              "took_place_at": [
                {
                  "id": "https://linkedart.example.com/Place/79088",
                  "type": "Place",
                  "classified_as": [
                    {
                      "id": "http://vocab.getty.edu/aat/300005768",
                      "type": "Type",
                      "_label": "Museum (place)"
                    }
                  ]
                }
              ]
            }
          ]
        }
      ]
    }
  ]
}