{
  "@context": "https://linked.art/ns/v1/linked-art.json",
  "id": "https://linkedart.example.com/exhibition/4411",
  "type": "Activity",
  "_label": "Paintings by Beauchamp, Cajori, Cohen, Dodd, Finkelstein, Groell, Ippolito, F. Mitchell, Maxwell, Pasilis, J.Sanders; Sculpture by King",
  "classified_as": [
    {
      "id": "http://vocab.getty.edu/aat/300054766",
      "type": "Type",
      "_label": "Exhibiting"
    }
  ],
  "identified_by": [
    {
      "type": "Name",
      "_label": "Paintings by Beauchamp, Cajori, Cohen, Dodd, Finkelstein, Groell, Ippolito, F. Mitchell, Maxwell, Pasilis, J.Sanders; Sculpture by King",
      "classified_as": [
        {
          "id": "http://vocab.getty.edu/aat/300404670",
          "type": "Type",
          "_label": "Owner-Assigned Title"
        }
      ]
    }
  ],
  "timespan": {
    "type": "TimeSpan",
    "begin_of_the_begin": "1952-21-5",
    "end_of_the_end": "1952-8-6"
  },
  "took_place_at": [
    {
      "id": "https://linkedart.example.com/Place/3305",
      "type": "Place",
      "_label": "51 East 4th Street",
      "classified_as": [
        {
          "id": "http://vocab.getty.edu/aat/300005768",
          "type": "Type",
          "_label": "Museum (place)"
        }
      ]
    }
  ],
  "part": [
    {
      "id": "https://linkedart.example.com/AttributeAssignment/3305",
      "type": "AttributeAssignment",
      "involved": [
        {
          "id": "https://linkedart.example.com/Set/4167",
          "type": "Set",
          "_label": "Artist",
          "about": [
            {
              "id": "https://linkedart.example.com/Person/27352",
              "type": "Person",
              "_label": "William D. King"
            },
            {
              "id": "https://linkedart.example.com/Person/27353",
              "type": "Person",
              "_label": "Jean Cohen"
            },
            {
              "id": "https://linkedart.example.com/Person/27354",
              "type": "Person",
              "_label": "Lois Dodd"
            },
            {
              "id": "https://linkedart.example.com/Person/27355",
              "type": "Person",
              "_label": "Louis Finkelstein"
            },
            {
              "id": "https://linkedart.example.com/Person/27356",
              "type": "Person",
              "_label": "Joseph Groell"
            },
            {
              "id": "https://linkedart.example.com/Person/27357",
              "type": "Person",
              "_label": "Angelo Ippolito"
            },
            {
              "id": "https://linkedart.example.com/Person/27358",
              "type": "Person",
              "_label": "Joop Sanders"
            },
            {
              "id": "https://linkedart.example.com/Person/27359",
              "type": "Person",
              "_label": "Robert Beauchamp"
            },
            {
              "id": "https://linkedart.example.com/Person/27360",
              "type": "Person",
              "_label": "Robert Maxwell"
            },
            {
              "id": "https://linkedart.example.com/Person/27361",
              "type": "Person",
              "_label": "Fred Mitchell"
            },
            {
              "id": "https://linkedart.example.com/Person/27362",
              "type": "Person",
              "_label": "Charles Cajori"
            },
            {
              "id": "https://linkedart.example.com/Person/27363",
              "type": "Person",
              "_label": "Felix Pasilis"
            }
          ]
        }
      ]
    }
  ]
}